augment/__init__.py
augment/effects.py
wavaugment-0.2.dist-info/LICENSE
wavaugment-0.2.dist-info/METADATA
wavaugment-0.2.dist-info/WHEEL
wavaugment-0.2.dist-info/top_level.txt
wavaugment-0.2.dist-info/RECORD
