Metadata-Version: 2.1
Name: wavaugment
Version: 0.2
Summary: UNKNOWN
Home-page: UNKNOWN
Author: UNKNOWN
Author-email: UNKNOWN
License: UNKNOWN
Platform: UNKNOWN
Requires-Dist: torch
Requires-Dist: torchaudio
